gitlab_ci_verify/__init__.py
gitlab_ci_verify/config.py
gitlab_ci_verify/model.py
gitlab_ci_verify/model_test.py
gitlab_ci_verify/parse.py
gitlab_ci_verify/parse_test.py
gitlab_ci_verify/process.py
gitlab_ci_verify/process_test.py
gitlab_ci_verify/verify.py
gitlab_ci_verify-2.8.3.dist-info/METADATA
gitlab_ci_verify-2.8.3.dist-info/WHEEL
gitlab_ci_verify-2.8.3.dist-info/top_level.txt
gitlab_ci_verify-2.8.3.dist-info/RECORD
