Metadata-Version: 2.2
Name: gitlab-ci-verify
Version: 2.8.3
Summary: Validate and lint your gitlab ci files using ShellCheck, the Gitlab API and curated checks
Author-email: Timo Reymann <mail@timo-reymann.de>
Classifier: License :: OSI Approved :: GNU General Public License v3 (GPLv3)
Classifier: Development Status :: 4 - Beta
Classifier: Programming Language :: Python :: 3
Classifier: Programming Language :: Python :: 3.9
Classifier: Programming Language :: Python :: 3.10
Classifier: Programming Language :: Python :: 3.11
Classifier: Programming Language :: Python :: 3.12
Classifier: Intended Audience :: Developers
Requires-Dist: gitlab-ci-verify-bin==2.*
Requires-Dist: coverage==7.13.*
Provides-Extra: dev
Requires-Dist: setuptools==75.*; extra == "dev"
Requires-Dist: setuptools-scm==8.*; extra == "dev"
Requires-Dist: twine==6.2.*; extra == "dev"
Requires-Dist: wheel==0.46.*; extra == "dev"
Requires-Dist: pydoctor==25.4.*; extra == "dev"
Requires-Dist: build==1.*; extra == "dev"
